{"title":"VIBE ─ 매거진","url":"https://vibe.naver.com/magazines","favicon":"https://vibe.naver.com/favicon.ico","elements":[{"title":"무엇이든 물어보세요 : \n이달의 소녀","contents":"<span data-v-103cea08=\"\" class=\"blind\">작성일</span> 2022.06.21","link":"https://vibe.naver.com/magazines/62132","retrieved":1656328524397},{"title":"New Release #97 : \n드레이크, 폴킴","contents":"<span data-v-103cea08=\"\" class=\"blind\">작성일</span> 2022.06.21","link":"https://vibe.naver.com/magazines/62131","retrieved":1655889343074,"image":"https://music-phinf.pstatic.net/20220621_151/1655795307789RQ8E1_GIF/%C4%BF%B9%F61.gif?type=w720"},{"title":"NEXTREND : \nLapillus(라필루스)","contents":"<span data-v-103cea08=\"\" class=\"blind\">작성일</span> 2022.06.20","link":"https://vibe.naver.com/magazines/62130","retrieved":1655800304756,"image":"https://music-phinf.pstatic.net/20220620_8/1655703729710I054C_JPEG/%C4%BF%B9%F61.jpg?type=w720"},{"title":"6월의 느낌, \n당신의 느낌은 어땠나요?","contents":"<span data-v-103cea08=\"\" class=\"blind\">작성일</span> 2022.06.17","link":"https://vibe.naver.com/magazines/62129","retrieved":1655716602475},{"title":"놓치면 아쉬워! : \n린린, 문수진","contents":"<span data-v-103cea08=\"\" class=\"blind\">작성일</span> 2022.06.16","link":"https://vibe.naver.com/magazines/62128","retrieved":1655454208553},{"title":"이주의 디깅 #136 \n포스트 말론","contents":"<span data-v-103cea08=\"\" class=\"blind\">작성일</span> 2022.06.14","link":"https://vibe.naver.com/magazines/62126","retrieved":1655370987878},{"title":"New Release #96 : \n방탄소년단, 할시","contents":"<span data-v-103cea08=\"\" class=\"blind\">작성일</span> 2022.06.13","link":"https://vibe.naver.com/magazines/62125","retrieved":1655256351529},{"title":"사랑과 갈등 사이 : \n화제의 예능 BGM","contents":"<span data-v-103cea08=\"\" class=\"blind\">작성일</span> 2022.06.09","link":"https://vibe.naver.com/magazines/62122","retrieved":1655115666894},{"title":"Lost & Found \nin Dvwn","contents":"<span data-v-103cea08=\"\" class=\"blind\">작성일</span> 2022.06.08","link":"https://vibe.naver.com/magazines/62124","retrieved":1655119007306},{"title":"이주의 디깅 #135 \n오프라인 공연","contents":"<span data-v-103cea08=\"\" class=\"blind\">작성일</span> 2022.06.07","link":"https://vibe.naver.com/magazines/62121","retrieved":1655111857927},{"title":"New Release #95 : \n포스트 말론, 포레스텔라","contents":"<span data-v-103cea08=\"\" class=\"blind\">작성일</span> 2022.06.07","link":"https://vibe.naver.com/magazines/62123","retrieved":1654672617257},{"title":"New Release #94 : \n세븐틴, 캘빈 해리스","contents":"<span data-v-103cea08=\"\" class=\"blind\">작성일</span> 2022.05.30","link":"https://vibe.naver.com/magazines/62120","retrieved":1654597405384}]}